my_krml_25552249/__init__.py
my_krml_25552249/data/sets.py
my_krml_25552249/features/dates.py
my_krml_25552249/features/impute.py
my_krml_25552249/features/selection.py
my_krml_25552249/models/null.py
my_krml_25552249/models/performance.py
my_krml_25552249/my_krml_25552249.py
my_krml_25552249-2025.0.7.2.dist-info/LICENSE
my_krml_25552249-2025.0.7.2.dist-info/METADATA
my_krml_25552249-2025.0.7.2.dist-info/WHEEL
my_krml_25552249-2025.0.7.2.dist-info/RECORD
