Metadata-Version: 2.3
Name: my_krml_25552249
Version: 2025.0.7.2
Summary: A package for doing great things!
License: MIT
Author: Shawya
Requires-Python: >=3.11.4,<4.0.0
Classifier: License :: OSI Approved :: MIT License
Classifier: Programming Language :: Python :: 3
Classifier: Programming Language :: Python :: 3.12
Classifier: Programming Language :: Python :: 3.13
Requires-Dist: pandas (==2.2.2)
Requires-Dist: scikit-learn (>=1.5.1,<2.0.0)
